odoo10_addon_purchase_request_procurement-10.0.1.1.0.99.dev5-nspkg.pth
odoo/addons/purchase_request_procurement/README.rst
odoo/addons/purchase_request_procurement/__init__.py
odoo/addons/purchase_request_procurement/__manifest__.py
odoo/addons/purchase_request_procurement/i18n/de.po
odoo/addons/purchase_request_procurement/i18n/es_PE.po
odoo/addons/purchase_request_procurement/i18n/fr.po
odoo/addons/purchase_request_procurement/i18n/hr.po
odoo/addons/purchase_request_procurement/i18n/nl_NL.po
odoo/addons/purchase_request_procurement/i18n/pt_BR.po
odoo/addons/purchase_request_procurement/i18n/purchase_request_procurement.pot
odoo/addons/purchase_request_procurement/i18n/sl.po
odoo/addons/purchase_request_procurement/migrations/10.0.1.1.0/post-migration.py
odoo/addons/purchase_request_procurement/models/__init__.py
odoo/addons/purchase_request_procurement/models/procurement_order.py
odoo/addons/purchase_request_procurement/models/product_template.py
odoo/addons/purchase_request_procurement/models/purchase_request.py
odoo/addons/purchase_request_procurement/models/purchase_request_line.py
odoo/addons/purchase_request_procurement/static/description/icon.png
odoo/addons/purchase_request_procurement/tests/__init__.py
odoo/addons/purchase_request_procurement/tests/test_purchase_request_procurement.py
odoo/addons/purchase_request_procurement/views/procurement_order.xml
odoo/addons/purchase_request_procurement/views/product_template.xml
odoo/addons/purchase_request_procurement/views/purchase_request_view.xml
odoo10_addon_purchase_request_procurement-10.0.1.1.0.99.dev5.dist-info/METADATA
odoo10_addon_purchase_request_procurement-10.0.1.1.0.99.dev5.dist-info/WHEEL
odoo10_addon_purchase_request_procurement-10.0.1.1.0.99.dev5.dist-info/namespace_packages.txt
odoo10_addon_purchase_request_procurement-10.0.1.1.0.99.dev5.dist-info/top_level.txt
odoo10_addon_purchase_request_procurement-10.0.1.1.0.99.dev5.dist-info/RECORD
