Metadata-Version: 2.1
Name: odoo10-addon-purchase-request-procurement
Version: 10.0.1.1.0.99.dev5
Summary: Purchase Request Procurement
Home-page: https://github.com/OCA/purchase-workflow
Author: Eficent Business and IT Consulting Services S.L., Odoo Community Association (OCA)
Author-email: support@odoo-community.org
License: LGPL-3
Platform: UNKNOWN
Classifier: Programming Language :: Python
Classifier: Framework :: Odoo
Classifier: License :: OSI Approved :: GNU Lesser General Public License v3 (LGPLv3)
Requires-Python: ~=2.7
Requires-Dist: odoo10-addon-purchase-request
Requires-Dist: odoo (<10.1dev,>=10.0)
